setup.cfg
setup.py
PasteWebKit.egg-info/PKG-INFO
PasteWebKit.egg-info/SOURCES.txt
PasteWebKit.egg-info/dependency_links.txt
PasteWebKit.egg-info/entry_points.txt
PasteWebKit.egg-info/namespace_packages.txt
PasteWebKit.egg-info/not-zip-safe
PasteWebKit.egg-info/requires.txt
PasteWebKit.egg-info/top_level.txt
docs/index.txt
docs/paste-webkit.txt
paste/__init__.py
paste/webkit/__init__.py
paste/webkit/servlet_script.py
paste/webkit/templates.py
paste/webkit/wkapplication.py
paste/webkit/wkcommon.py
paste/webkit/wkrequest.py
paste/webkit/wkresponse.py
paste/webkit/wkservlet.py
paste/webkit/wksession.py
paste/webkit/wktransaction.py
paste/webkit/wsgiapp.py
paste/webkit/FakeWebware/README.txt
paste/webkit/FakeWebware/__init__.py
paste/webkit/FakeWebware/MiscUtils/CSVJoiner.py
paste/webkit/FakeWebware/MiscUtils/CSVParser.py
paste/webkit/FakeWebware/MiscUtils/DBPool.py
paste/webkit/FakeWebware/MiscUtils/DataTable.py
paste/webkit/FakeWebware/MiscUtils/DateInterval.py
paste/webkit/FakeWebware/MiscUtils/DictForArgs.py
paste/webkit/FakeWebware/MiscUtils/Error.py
paste/webkit/FakeWebware/MiscUtils/Funcs.py
paste/webkit/FakeWebware/MiscUtils/M2PickleRPC.py
paste/webkit/FakeWebware/MiscUtils/MixIn.py
paste/webkit/FakeWebware/MiscUtils/NamedValueAccess.py
paste/webkit/FakeWebware/MiscUtils/ParamFactory.py
paste/webkit/FakeWebware/MiscUtils/PickleCache.py
paste/webkit/FakeWebware/MiscUtils/PickleRPC.py
paste/webkit/FakeWebware/MiscUtils/PropertiesObject.py
paste/webkit/FakeWebware/MiscUtils/__init__.py
paste/webkit/FakeWebware/TaskKit/Properties.py
paste/webkit/FakeWebware/TaskKit/Scheduler.py
paste/webkit/FakeWebware/TaskKit/Task.py
paste/webkit/FakeWebware/TaskKit/TaskHandler.py
paste/webkit/FakeWebware/TaskKit/__init__.py
paste/webkit/FakeWebware/TaskKit/Docs/GenIndex.css
paste/webkit/FakeWebware/TaskKit/Docs/QuickStart.html
paste/webkit/FakeWebware/TaskKit/Docs/RelNotes-0.1.1.html
paste/webkit/FakeWebware/TaskKit/Docs/RelNotes-0.7.html
paste/webkit/FakeWebware/TaskKit/Docs/RelNotes-0.8.html
paste/webkit/FakeWebware/TaskKit/Docs/RelNotes-X.Y.html
paste/webkit/FakeWebware/TaskKit/Docs/StyleSheet.css
paste/webkit/FakeWebware/TaskKit/Docs/TODO-TaskKit.text
paste/webkit/FakeWebware/TaskKit/Docs/UsersGuide.html
paste/webkit/FakeWebware/TaskKit/Docs/index.html
paste/webkit/paster_templates/webkit/+project+.egg-info/sqlobject.txt_tmpl
