Metadata-Version: 1.0
Name: PasteWebKit
Version: 1.0
Summary: A port/reimplementation of Webware WebKit in WSGI and Paste
Home-page: http://pythonpaste.org/webkit/
Author: Ian Bicking
Author-email: ianb@colorstudy.com
License: UNKNOWN
Keywords: web wsgi application framework webware webkit
Platform: UNKNOWN
Classifier: Development Status :: 5 - Production/Stable
Classifier: Intended Audience :: Developers
Classifier: License :: OSI Approved :: MIT License
Classifier: Programming Language :: Python
Classifier: Topic :: Internet :: WWW/HTTP
Classifier: Topic :: Internet :: WWW/HTTP :: Dynamic Content
Classifier: Topic :: Software Development :: Libraries :: Python Modules
Classifier: Topic :: Internet :: WWW/HTTP :: WSGI
Classifier: Topic :: Internet :: WWW/HTTP :: WSGI :: Application
Classifier: Framework :: Paste
